s2aio/__init__.py
s2aio/__main__.py
s2aio/ScratchFiles/ScratchProjects/s2aio_base.sb2
s2aio/ScratchFiles/ScratchProjects/s2aio_base_DE.sb2
s2aio/ScratchFiles/ScratchProjects/s2aio_base_ES.sb2
s2aio/ScratchFiles/ScratchProjects/s2aio_base_FR.sb2
s2aio/ScratchFiles/ScratchProjects/s2aio_base_GR.sb2
s2aio/ScratchFiles/ScratchProjects/s2aio_base_IT.sb2
s2aio/ScratchFiles/ScratchProjects/s2aio_base_KO.sb2
s2aio/ScratchFiles/ScratchProjects/s2aio_base_NL.sb2
s2aio/ScratchFiles/ScratchProjects/s2aio_base_PL.sb2
s2aio/ScratchFiles/ScratchProjects/s2aio_base_PT.sb2
s2aio/ScratchFiles/ScratchProjects/s2aio_base_zh_CN.sb2
s2aio/ScratchFiles/ScratchProjects/s2aio_base_zh_TW.sb2
s2aio/Snap!Files/s2aio_Snap_base.xml
s2aio/Snap!Files/s2aio_Snap_base_DE.xml
s2aio/Snap!Files/s2aio_Snap_base_ES.xml
s2aio/Snap!Files/s2aio_Snap_base_FR.xml
s2aio/Snap!Files/s2aio_Snap_base_GR.xml
s2aio/Snap!Files/s2aio_Snap_base_IT.xml
s2aio/Snap!Files/s2aio_Snap_base_KO.xml
s2aio/Snap!Files/s2aio_Snap_base_NL.xml
s2aio/Snap!Files/s2aio_Snap_base_PL.xml
s2aio/Snap!Files/s2aio_Snap_base_PT.xml
s2aio/Snap!Files/s2aio_Snap_base_zh_CN.xml
s2aio/Snap!Files/s2aio_Snap_base_zh_TW.xml
s2aio/configuration/configuration.cfg
s2aio-1.17.dist-info/METADATA
s2aio-1.17.dist-info/RECORD
s2aio-1.17.dist-info/WHEEL
s2aio-1.17.dist-info/entry_points.txt
s2aio-1.17.dist-info/top_level.txt
