Metadata-Version: 2.1
Name: s2aio
Version: 1.17
Summary: A Scratch 2.0 (Offline) Hardware Extension for Arduino
Home-page: https://github.com/MrYsLab/s2aio/wiki
Author: Alan Yorinks
Author-email: MisterYsLab@gmail.com
License: GNU General Public License v3 (GPLv3)
Download-URL: https://github.com/MrYsLab/s2aio
Keywords: Firmata,Arduino,Scratch
Platform: UNKNOWN
Classifier: Development Status :: 5 - Production/Stable
Classifier: Environment :: Other Environment
Classifier: Intended Audience :: Education
Classifier: License :: OSI Approved :: GNU General Public License v3 or later (GPLv3+)
Classifier: Operating System :: OS Independent
Classifier: Programming Language :: Python :: 3.5
Classifier: Programming Language :: Python :: 3.6
Classifier: Programming Language :: Python :: 3.7
Classifier: Programming Language :: Python :: 3 :: Only
Classifier: Topic :: Education
Requires-Dist: pymata-aio (>=2.22)
Requires-Dist: aiohttp (>=3.3.2)
